smsing/Preprocesser.py
smsing/__init__.py
smsing/errors.py
smsing/extraction/__init__.py
smsing/extraction/extract.py
smsing/preprocessing/__init__.py
smsing/preprocessing/errors.py
smsing/preprocessing/filter.py
smsing/preprocessing/remove.py
smsing/preprocessing/tokenize.py
smsing/preprocessing/transform.py
smsing/topic_modeling/TmModel.py
smsing/topic_modeling/__init__.py
smsing/topic_modeling/plot.py
smsing/topic_modeling/topic_modeling_methods.py
smsing-0.0.4.dist-info/LICENSE.txt
smsing-0.0.4.dist-info/METADATA
smsing-0.0.4.dist-info/WHEEL
smsing-0.0.4.dist-info/top_level.txt
smsing-0.0.4.dist-info/RECORD
