Metadata-Version: 2.1
Name: smsing
Version: 0.0.4
Summary: Preprocessing and ML methods for social media
Home-page: https://github.com/roiprez/smsing
Author: Roi Pérez López
Author-email: roiprezl@gmail.com
License: MIT
Platform: UNKNOWN
Classifier: License :: OSI Approved :: MIT License
Classifier: Programming Language :: Python :: 3
Classifier: Programming Language :: Python :: 3.7
Requires-Dist: gensim
Requires-Dist: scikit-learn
Requires-Dist: pandas
Requires-Dist: nltk
Requires-Dist: spacy
Requires-Dist: beautifulsoup4
Requires-Dist: lxml
